naver_blog_seo/__init__.py
naver_blog_seo/cli.py
naver_blog_seo/core.py
naver_blog_seo/models.py
naver_blog_seo/skills/naver-blog-audit.md
naver_blog_seo/skills/naver-blog-seo.md
naver_blog_seo-0.1.2.dist-info/licenses/LICENSE
tests/test_loader.py
tests/test_pydantic.py
naver_blog_seo-0.1.2.dist-info/METADATA
naver_blog_seo-0.1.2.dist-info/WHEEL
naver_blog_seo-0.1.2.dist-info/entry_points.txt
naver_blog_seo-0.1.2.dist-info/top_level.txt
naver_blog_seo-0.1.2.dist-info/RECORD
