Metadata-Version: 2.4
Name: naver-blog-seo
Version: 0.1.2
Summary: A Python wrapper for Naver Blog SEO optimization skills
Author-email: Claude <claude@anthropic.com>
License: MIT
Project-URL: Homepage, https://github.com/doric9/naver-blog-seo
Project-URL: Bug Tracker, https://github.com/doric9/naver-blog-seo/issues
Classifier: Programming Language :: Python :: 3
Classifier: License :: OSI Approved :: MIT License
Classifier: Operating System :: OS Independent
Classifier: Topic :: Software Development :: Libraries :: Python Modules
Classifier: Intended Audience :: Developers
Requires-Python: >=3.9
License-File: LICENSE
Requires-Dist: pydantic>=2.0.0
Dynamic: license-file
